Metadata-Version: 2.1
Name: wrist-english
Version: 1.0.1
Summary: Lightweight online translation tool created for learners.
Home-page: https://github.com/wristwaking/python
Author: 唤醒手腕
Author-email: 1620444902@qq.com
License: MIT License
Keywords: english
Platform: any
